NuPy/__init__.py
NuPy/oscprobs.py
NuPy/utils.py
nupyosc-0.0.2.dist-info/METADATA
nupyosc-0.0.2.dist-info/WHEEL
nupyosc-0.0.2.dist-info/top_level.txt
nupyosc-0.0.2.dist-info/RECORD
